cpu/2_ID_RF_STAGE/reg_file.v
`timescale 1ns/100ps

module reg_file (WRITE_DATA, DATA_OUT1, DATA_OUT2, WRITE_ADDR, OUT_ADDR1, OUT_ADDR2, WRITE_ENABLE, CLK, RESET);

    // Defining input/output ports
    input WRITE_ENABLE, CLK, RESET;
    input [4:0] WRITE_ADDR, OUT_ADDR1, OUT_ADDR2;
    input [31:0] WRITE_DATA;
    output [31:0] DATA_OUT1, DATA_OUT2;

    // The register file is a 32x32 array of registers
    // Each register is 32 bits wide, and there are 32 registers
    reg [31:0] REGISTERS [31:0];

    // Reading the registers
    // Asynchronous read, this runs when the register values change
    assign #2 DATA_OUT1 = REGISTERS[OUT_ADDR1];
    assign #2 DATA_OUT2 = REGISTERS[OUT_ADDR2];

    // Writes must happen on the negative clock edge
    integer i;
    always @ (negedge CLK) 
    begin
        // Reset the registers if RESET is high
        // If RESET is high, all registers are set to 0
        if (RESET)
            for (i = 0; i < 32; i = i + 1)
                REGISTERS[i] <= #1 32'd0;       
        else
            if (WRITE_ENABLE && (WRITE_ADDR !== 5'd0))     // Register x0 cannot be written to
                REGISTERS[WRITE_ADDR] <= #1 WRITE_DATA; // Corrected from IN_ADDR to WRITE_ADDR
    end

endmodule

cpu/2_ID_RF_STAGE/reg_file_tb.v
`include "reg_file.v"
`timescale 1ns/100ps

module reg_file_tb;
    
    // Defining input/output ports
    reg WRITE_ENABLE, CLK, RESET;
    reg [4:0] WRITE_ADDR, OUT_ADDR1, OUT_ADDR2;
    reg [31:0] WRITE_DATA;
    wire [31:0] DATA_OUT1, DATA_OUT2;

    // Instantiate the register file module
    reg_file reg_file_t(
        .WRITE_ENABLE(WRITE_ENABLE),
        .CLK(CLK),
        .RESET(RESET),
        .WRITE_ADDR(WRITE_ADDR),
        .OUT_ADDR1(OUT_ADDR1),
        .OUT_ADDR2(OUT_ADDR2),
        .WRITE_DATA(WRITE_DATA),
        .DATA_OUT1(DATA_OUT1),
        .DATA_OUT2(DATA_OUT2)
    );

    // Clock generation
    initial begin
        CLK = 1;
        forever #5 CLK = ~CLK; // Toggle clock every 5 time units
    end

    // Testbench logic
    initial begin

        // generate files needed to plot the waveform using GTKWave
        $dumpfile("reg_file_tb.vcd");
        $dumpvars(0, reg_file_tb);
        $monitor("Time: %0t | WRITE_ENABLE: %b | WRITE_ADDR: %d | OUT_ADDR1: %d | OUT_ADDR2: %d | WRITE_DATA: %d | DATA_OUT1: %d | DATA_OUT2: %d", 
                 $time, WRITE_ENABLE, WRITE_ADDR, OUT_ADDR1, OUT_ADDR2, WRITE_DATA, DATA_OUT1, DATA_OUT2);

    
        // Initialize inputs
        RESET = 1; // Assert reset
        WRITE_ENABLE = 0;
        WRITE_ADDR = 5'd0;
        OUT_ADDR1 = 5'd0;
        OUT_ADDR2 = 5'd0;
        WRITE_DATA = 32'd0;

        // Wait for a few clock cycles
        #10;

        // Deassert reset
        RESET = 0;
        #10;

        // Test writing to the register file
        WRITE_ENABLE = 1;
        WRITE_ADDR = 5'd1; // Write to register 1
        WRITE_DATA = 32'd42; // Write value 42
        #10; // Wait for a clock cycle
        WRITE_ENABLE = 0; // Disable write
        
        #10; // Wait for a clock cycle
        OUT_ADDR1 = 5'd1; // Read from register 1
        OUT_ADDR2 = 5'd0; // Read from register 0 (should always be 0)
        #10; // Wait for a clock cycle
        // Check outputs
        if (DATA_OUT1 !== 32'd42) begin
            $display("Test failed: DATA_OUT1 = %d, expected 42", DATA_OUT1);
        end else begin
            $display("Test passed: DATA_OUT1 = %d", DATA_OUT1);
        end
        if (DATA_OUT2 !== 32'd0) begin
            $display("Test failed: DATA_OUT2 = %d, expected 0", DATA_OUT2);
        end else begin
            $display("Test passed: DATA_OUT2 = %d", DATA_OUT2);
        end

        // Test writing to another register
        #10;
        WRITE_ENABLE = 1;
        WRITE_ADDR = 5'd2; // Write to register 2
        WRITE_DATA = 32'd100; // Write value 100
        #10; // Wait for a clock cycle
        WRITE_ENABLE = 0; // Disable write


        #10; // Wait for a clock cycle
        OUT_ADDR1 = 5'd2; // Read from register 2
        OUT_ADDR2 = 5'd1; // Read from register 1
        #10; // Wait for a clock cycle
        // Check outputs
        if (DATA_OUT1 !== 32'd100) begin
            $display("Test failed: DATA_OUT1 = %d, expected 100", DATA_OUT1);
        end else begin
            $display("Test passed: DATA_OUT1 = %d", DATA_OUT1);
        end
        if (DATA_OUT2 !== 32'd42) begin
            $display("Test failed: DATA_OUT2 = %d, expected 42", DATA_OUT2);
        end else begin
            $display("Test passed: DATA_OUT2 = %d", DATA_OUT2);
        end

        // Test writing to register 0 (should not change value)
        #10;
        WRITE_ENABLE = 1;
        WRITE_ADDR = 5'd0; // Write to register 0 (should not change value)
        WRITE_DATA = 32'd123; // Write value 123
        #10; // Wait for a clock cycle
        WRITE_ENABLE = 0; // Disable write

        OUT_ADDR1 = 5'd0; // Read from register 0
        OUT_ADDR2 = 5'd1; // Read from register 1
        #10; // Wait for a clock cycle
        // Check outputs
        if (DATA_OUT1 !== 32'd0) begin
            $display("Test failed: DATA_OUT1 = %d, expected 0", DATA_OUT1);
        end else begin
            $display("Test passed: DATA_OUT1 = %d", DATA_OUT1);
        end
        if (DATA_OUT2 !== 32'd42) begin
            $display("Test failed: DATA_OUT2 = %d, expected 42", DATA_OUT2);
        end else begin
            $display("Test passed: DATA_OUT2 = %d", DATA_OUT2);
        end

        $finish;

    end

endmodule

cpu/2_ID_RF_STAGE/reg_file_tb.vcd
$date
	Thu May 01 19:37:28 2025
$end
$version
	Icarus Verilog
$end
$timescale
	100ps
$end
$scope module reg_file_tb $end
$var wire 32 ! DATA_OUT2 [31:0] $end
$var wire 32 " DATA_OUT1 [31:0] $end
$var reg 1 # CLK $end
$var reg 5 $ OUT_ADDR1 [4:0] $end
$var reg 5 % OUT_ADDR2 [4:0] $end
$var reg 1 & RESET $end
$var reg 5 ' WRITE_ADDR [4:0] $end
$var reg 32 ( WRITE_DATA [31:0] $end
$var reg 1 ) WRITE_ENABLE $end
$scope module reg_file_t $end
$var wire 1 # CLK $end
$var wire 32 * DATA_OUT1 [31:0] $end
$var wire 32 + DATA_OUT2 [31:0] $end
$var wire 5 , OUT_ADDR1 [4:0] $end
$var wire 5 - OUT_ADDR2 [4:0] $end
$var wire 1 & RESET $end
$var wire 5 . WRITE_ADDR [4:0] $end
$var wire 32 / WRITE_DATA [31:0] $end
$var wire 1 ) WRITE_ENABLE $end
$var integer 32 0 i [31:0] $end
$upscope $end
$upscope $end
$enddefinitions $end
$comment Show the parameter values. $end
$dumpall
$end
#0
$dumpvars
bx 0
b0 /
b0 .
b0 -
b0 ,
bx +
bx *
0)
b0 (
b0 '
1&
b0 %
b0 $
1#
bx "
bx !
$end
#50
b100000 0
0#
#80
b0 "
b0 *
b0 !
b0 +
#100
1#
0&
#150
0#
#200
1#
b101010 (
b101010 /
b1 '
b1 .
1)
#250
0#
#300
1#
0)
#350
0#
#400
1#
b1 $
b1 ,
#420
b101010 "
b101010 *
#450
0#
#500
1#
#550
0#
#600
1#
b1100100 (
b1100100 /
b10 '
b10 .
1)
#650
0#
#700
1#
0)
#750
0#
#800
1#
b1 %
b1 -
b10 $
b10 ,
#820
b101010 !
b101010 +
b1100100 "
b1100100 *
#850
0#
#900
1#
#950
0#
#1000
1#
b1111011 (
b1111011 /
b0 '
b0 .
1)
#1050
0#
#1100
1#
b0 $
b0 ,
0)
#1120
b0 "
b0 *
